DynamicScheduler/__init__.py
DynamicScheduler/dynamic_scheduler.py
DynamicScheduler/scheduler_utils.py
dynamic_scheduler-1.0.2.dist-info/LICENSE
dynamic_scheduler-1.0.2.dist-info/METADATA
dynamic_scheduler-1.0.2.dist-info/WHEEL
dynamic_scheduler-1.0.2.dist-info/top_level.txt
dynamic_scheduler-1.0.2.dist-info/RECORD
