Metadata-Version: 2.1
Name: dynamic-scheduler
Version: 1.0.2
Summary: 动态的带结果保存的定时任务管理器
Home-page: https://github.com/AlitaIcon/dynamic-scheduler
Author: alita
Author-email: 1906321518@qq.com
License: MIT
Project-URL: Documentation, https://github.com/AlitaIcon/dynamic-scheduler
Platform: UNKNOWN
Classifier: Programming Language :: Python :: 3
Classifier: License :: OSI Approved :: MIT License
Classifier: Operating System :: OS Independent
Requires-Python: >=3.6
Requires-Dist: PoolDB (>=0.0.5)
Requires-Dist: apscheduler (>=3.7.0)
